mmd_critic/__init__.py
mmd_critic/mmd.py
mmd_critic/mmd_critic.py
mmd_critic/kernels/__init__.py
mmd_critic/kernels/kernel.py
mmd_critic/kernels/rbf_kernel.py
tests/__init__.py
tests/test_mmd.py
tests/test_mmd_critic.py
tests/test_kernels/__init__.py
tests/test_kernels/test_rbf_kernel.py
mmd_critic-0.1.2.dist-info/LICENSE
mmd_critic-0.1.2.dist-info/METADATA
mmd_critic-0.1.2.dist-info/WHEEL
mmd_critic-0.1.2.dist-info/top_level.txt
mmd_critic-0.1.2.dist-info/RECORD
