Metadata-Version: 2.1
Name: mmd-critic
Version: 0.1.2
Summary: Python package for the MMD Critic method
Home-page: https://github.com/PhysBoom/mmd_critic
Author: Matthew Chak
Author-email: mchak@calpoly.edu
License: MIT
Classifier: Programming Language :: Python :: 3
Classifier: License :: OSI Approved :: MIT License
Classifier: Operating System :: OS Independent
Requires-Python: >=3.6
License-File: LICENSE
Requires-Dist: numpy
Requires-Dist: numexpr
